mongo_to_geojson/__init__.py
mongo_to_geojson/command_line.py
mongo_to_geojson-0.2.dist-info/METADATA
mongo_to_geojson-0.2.dist-info/RECORD
mongo_to_geojson-0.2.dist-info/WHEEL
mongo_to_geojson-0.2.dist-info/entry_points.txt
mongo_to_geojson-0.2.dist-info/top_level.txt
