Metadata-Version: 2.1
Name: mongo-to-geojson
Version: 0.2
Summary: extract geojson from Mongo
Home-page: https://github.com/westchamp24/mongo_to_geojson
Author: Rafael Ferraro
Author-email: rafael.m.ferraro@gmail.com
License: MIT
Keywords: mongo geojson
Platform: UNKNOWN
Classifier: Intended Audience :: Developers
Classifier: License :: OSI Approved :: BSD License
Classifier: Programming Language :: Python :: 3
Classifier: Topic :: Software Development :: Libraries :: Python Modules
Requires-Dist: click (>=6.7)
Requires-Dist: pymongo (>=3.7.1)
